LICENSE
MANIFEST.in
README.md
requirements.txt
setup.py
telegram_menu/__init__.py
telegram_menu/_version.py
telegram_menu/models.py
telegram_menu/navigation.py
telegram_menu/py.typed
telegram_menu.egg-info/PKG-INFO
telegram_menu.egg-info/SOURCES.txt
telegram_menu.egg-info/dependency_links.txt
telegram_menu.egg-info/not-zip-safe
telegram_menu.egg-info/requires.txt
telegram_menu.egg-info/top_level.txt
tests/__init__.py
tests/demo.py
tests/test_connection.py