Metadata-Version: 2.1
Name: telegram-menu
Version: 0.3.14
Summary: A python library to generate navigation menus using Telegram Bot API.
Home-page: https://github.com/mevellea/telegram_menu
Author: Armel Mevellec
Author-email: mevellea@gmail.com
License: GNU GPLv3
Keywords: telegram
Platform: any
Classifier: Development Status :: 4 - Beta
Classifier: Intended Audience :: Developers
Classifier: License :: OSI Approved :: GNU General Public License v3 (GPLv3)
Classifier: Operating System :: OS Independent
Classifier: Topic :: Software Development :: Libraries
Classifier: Programming Language :: Python :: 3.6
Classifier: Programming Language :: Python :: 3.7
Classifier: Programming Language :: Python :: 3.8
License-File: LICENSE
